{"data":{"_id":1000,"properties":{"id":{"name":"id","kind":"scalar","primary":true,"type":"uuid","nullable":false,"comment":"User ID","array":false,"runtimeType":"string"},"username":{"name":"username","kind":"scalar","type":"varchar","length":128,"nullable":false,"comment":"Username","getter":false,"setter":false,"array":false,"runtimeType":"string"},"password":{"name":"password","kind":"scalar","type":"varchar","hidden":true,"comment":"User password","getter":false,"setter":false,"array":false,"runtimeType":"string"},"favouriteMovies":{"name":"favouriteMovies","kind":"1:m","cascade":["persist"],"type":"UserMovieEntity","array":false,"runtimeType":"Collection<UserMovieEntity, object>"},"reviewedMovies":{"name":"reviewedMovies","kind":"1:m","cascade":["persist"],"type":"MovieReviewEntity","array":false,"runtimeType":"Collection<MovieReviewEntity, object>"}},"primaryKeys":["id"],"filters":{},"hooks":{},"indexes":[],"uniques":[],"className":"UserEntity","path":"./dist/src/entities/users.entity.js","collection":"users","name":"UserEntity","abstract":false,"internal":true,"constructorParams":["param","favouriteMovies","reviewedMovies"],"toJsonParams":[],"extends":"BaseEntity","useCache":true,"compositePK":false,"simplePK":true},"origin":"./dist/src/entities/users.entity.js","hash":"071d314d8621093b45007f4f666b8b35","version":"6.1.0"}
